{
  "factory": "comdex149ltwdnpxrhx9al42s359glcjnsuc6x3dalz28f04dsxhlu7jhmq3anmuq",
  "vaults": [
    {
      "pool_id": "USDT",
      "vault_assets": {
        "id": "comdex",
        "chain_id": "comdex-1",
        "token_address": "ucmst",
        "symbol": "CMST",
        "name": "CMST",
        "decimals": 6,
        "logoURI": "/logos/usdt.png",
        "tags": ["native"],
        "native": true,
        "denom": "ucmst"
      },
      "lp_token": "comdex1guczj53xxl4347adagh23eelyhnxvugw2nqq0q0dr6kws7q35jyqzf9hkm",
      "vault_address": "comdex19hlynxzedrlqv99v6qscww7d3crhl86qtd0vprpltg5g9xx6jk9qcmxed5",
      "staking_address": "",
      "rewards_tokens": []
    }
  ]
}
